zoo_runner_common/__init__.py
zoo_runner_common/base_runner.py
zoo_runner_common/handlers.py
zoo_runner_common/zoo_conf.py
zoo_runner_common/zoostub.py
zoo_runner_common-0.1.3.dist-info/METADATA
zoo_runner_common-0.1.3.dist-info/WHEEL
zoo_runner_common-0.1.3.dist-info/top_level.txt
zoo_runner_common-0.1.3.dist-info/RECORD
