Metadata-Version: 2.4
Name: zoo-runner-common
Version: 0.1.3
Summary: Shared utilities for ZOO-Project CWL runners
Author-email: Aryan Khare <kharearyan78@gmail.com>, Gérald Fenoy <gerald.fenoy@geolabs.fr>
License: Apache-2.0
Project-URL: Homepage, https://github.com/ZOO-Project/zoo-runner-common
Project-URL: Documentation, https://zoo-project.github.io/zoo-runner-common/
Project-URL: Repository, https://github.com/ZOO-Project/zoo-runner-common
Project-URL: Issues, https://github.com/ZOO-Project/zoo-runner-common/issues
Project-URL: Changelog, https://github.com/ZOO-Project/zoo-runner-common/blob/main/CHANGELOG.md
Keywords: zoo-project,cwl,runner,workflow,ogc,api,processes
Classifier: Development Status :: 4 - Beta
Classifier: Intended Audience :: Developers
Classifier: License :: OSI Approved :: Apache Software License
Classifier: Programming Language :: Python :: 3
Classifier: Programming Language :: Python :: 3.10
Classifier: Programming Language :: Python :: 3.11
Classifier: Programming Language :: Python :: 3.12
Classifier: Topic :: Software Development :: Libraries :: Python Modules
Requires-Python: >=3.10
Requires-Dist: loguru>=0.7.0
